CHANGES.rst
CONTRIBUTING.rst
MANIFEST.in
README.rst
setup.cfg
setup.py
docs/HISTORY-old.txt
docs/LICENSE.GPL
docs/LICENSE.txt
docs/contributors.rst
plone/__init__.py
plone.formwidget.datetime.egg-info/PKG-INFO
plone.formwidget.datetime.egg-info/SOURCES.txt
plone.formwidget.datetime.egg-info/dependency_links.txt
plone.formwidget.datetime.egg-info/entry_points.txt
plone.formwidget.datetime.egg-info/namespace_packages.txt
plone.formwidget.datetime.egg-info/not-zip-safe
plone.formwidget.datetime.egg-info/requires.txt
plone.formwidget.datetime.egg-info/top_level.txt
plone/formwidget/__init__.py
plone/formwidget/datetime/__init__.py
plone/formwidget/datetime/base.py
plone/formwidget/datetime/configure.zcml
plone/formwidget/datetime/setuphandlers.py
plone/formwidget/datetime/testing.py
plone/formwidget/datetime/at/__init__.py
plone/formwidget/datetime/at/configure.zcml
plone/formwidget/datetime/at/testing.py
plone/formwidget/datetime/at/widget.py
plone/formwidget/datetime/at/browser/__init__.py
plone/formwidget/datetime/at/browser/configure.zcml
plone/formwidget/datetime/at/browser/datetime_input.pt
plone/formwidget/datetime/at/browser/widget.py
plone/formwidget/datetime/at/tests/__init__.py
plone/formwidget/datetime/at/tests/test.pt
plone/formwidget/datetime/at/tests/test_BaseWidget.py
plone/formwidget/datetime/at/tests/test_DateWidget.py
plone/formwidget/datetime/at/tests/test_DatetimeWidget.py
plone/formwidget/datetime/at/tests/test_MonthYearWidget.py
plone/formwidget/datetime/at/tests/test_YearWidget.py
plone/formwidget/datetime/at/tests/test_datetime.py
plone/formwidget/datetime/at/tests/test_integration.py
plone/formwidget/datetime/at/tests/testv.pt
plone/formwidget/datetime/at/tests/examples/DatetimeWidgetType.py
plone/formwidget/datetime/at/tests/examples/__init__.py
plone/formwidget/datetime/at/tests/examples/configure.zcml
plone/formwidget/datetime/at/tests/examples/profiles/examples/archetype_tool.xml
plone/formwidget/datetime/at/tests/examples/profiles/examples/metadata.xml
plone/formwidget/datetime/at/tests/examples/profiles/examples/types.xml
plone/formwidget/datetime/at/tests/examples/profiles/examples/types/DatetimeWidgetType.xml
plone/formwidget/datetime/profiles/default/cssregistry.xml
plone/formwidget/datetime/profiles/default/jsregistry.xml
plone/formwidget/datetime/profiles/default/metadata.xml
