Metadata-Version: 1.1
Name: plone.formwidget.datetime
Version: 1.3
Summary: Datetime widgets for Plone
Home-page: https://github.com/plone/plone.formwidget.datetime
Author: Plone Foundation
Author-email: plone-developers@lists.sourceforge.net
License: GPL
Keywords: plone date time datetime event widget archetypes z3c.form
Platform: UNKNOWN
Classifier: Framework :: Plone
Classifier: Framework :: Plone :: 5.0
Classifier: Programming Language :: Python
Classifier: Programming Language :: Python :: 2.7
